flippy/__init__.py
flippy/apps.py
flippy/backends/__init__.py
flippy/backends/base.py
flippy/backends/django.py
flippy/backends/flipper_cloud.py
flippy/backends/memory.py
flippy/config.py
flippy/context.py
flippy/core.py
flippy/exceptions.py
flippy/flippy.py
flippy/gates.py
flippy/management/__init__.py
flippy/management/commands/__init__.py
flippy/management/commands/sync-from-cloud.py
flippy/middleware.py
flippy/migrations/0001_initial.py
flippy/migrations/__init__.py
flippy/models.py
django_flippy-0.9.0.dist-info/LICENSE.txt
django_flippy-0.9.0.dist-info/METADATA
django_flippy-0.9.0.dist-info/WHEEL
django_flippy-0.9.0.dist-info/RECORD
